lcdc/__init__.py
lcdc/dataset_builder.py
lcdc/lcdataset.py
lcdc/stats.py
lcdc/vars.py
lcdc/preprocessing/__init__.py
lcdc/preprocessing/filter.py
lcdc/preprocessing/preprocessor.py
lcdc/preprocessing/splits.py
lcdc/preprocessing/transformations.py
lcdc/utils/__init__.py
lcdc/utils/functions.py
lcdc-0.1.2.dist-info/licenses/LICENSE
lcdc-0.1.2.dist-info/METADATA
lcdc-0.1.2.dist-info/WHEEL
lcdc-0.1.2.dist-info/top_level.txt
lcdc-0.1.2.dist-info/RECORD
