Metadata-Version: 2.4
Name: lcdc
Version: 0.1.2
Home-page: https://github.com/lcdc-develop/lcdc
License: MIT
Project-URL: Documentation, https://lcdc-develop.github.io/lcdc/
Project-URL: Source, https://github.com/lcdc-develop/lcdc
License-File: LICENSE
Requires-Dist: scikit-learn
Requires-Dist: numpy
Requires-Dist: pyarrow
Requires-Dist: matplotlib
Requires-Dist: PyWavelets
Requires-Dist: datasets
Requires-Dist: tqdm
Requires-Dist: strenum
Dynamic: description
Dynamic: description-content-type
Dynamic: home-page
Dynamic: license
Dynamic: license-file
Dynamic: project-url
Dynamic: requires-dist
